pokedex_api/__init__.py
pokedex_api/api.py
pokedex_api-0.1.0.dist-info/LICENSE
pokedex_api-0.1.0.dist-info/METADATA
pokedex_api-0.1.0.dist-info/WHEEL
pokedex_api-0.1.0.dist-info/top_level.txt
pokedex_api-0.1.0.dist-info/RECORD
