Metadata-Version: 2.1
Name: pokedex-api
Version: 0.1.0
Summary: A simple API wrapper for accessing Pokémon information.
Home-page: https://github.com/AndrewAMur/pokedex-api
Author: Andrew Muratov
Author-email: andrewamuratov@gmail.com
License: MIT
License-File: LICENSE
Requires-Dist: requests
